yamlpage.py
yamlpage-3.2.0.dist-info/METADATA
yamlpage-3.2.0.dist-info/WHEEL
yamlpage-3.2.0.dist-info/top_level.txt
yamlpage-3.2.0.dist-info/RECORD
