Metadata-Version: 2.1
Name: yamlpage
Version: 3.2.0
Summary: Flatpages based on files with yaml syntax
Home-page: https://github.com/imbolc/yamlpage
Author: Imbolc
Author-email: imbolc@imbolc.name
License: ISC
Platform: UNKNOWN
Classifier: Development Status :: 4 - Beta
Classifier: Intended Audience :: Developers
Classifier: License :: OSI Approved :: ISC License (ISCL)
Classifier: Programming Language :: Python
Classifier: Programming Language :: Python :: 3
Requires-Dist: pyyaml
